setup.py
happynumber/__init__.py
happynumber.egg-info/PKG-INFO
happynumber.egg-info/SOURCES.txt
happynumber.egg-info/dependency_links.txt
happynumber.egg-info/not-zip-safe
happynumber.egg-info/top_level.txt