Metadata-Version: 1.0
Name: happynumber
Version: 0.1
Summary: Find out if a number is a happy number (aka cool number)
Home-page: http://github.com/tanhaa/happynumber
Author: Amit Malhotra
Author-email: tanhaa@tanhaa.net
License: MIT
Platform: UNKNOWN
